LICENSE
README.md
setup.cfg
setup.py
pixabay/__init__.py
pixabay/core.py
pixabay/image.py
pixabay/params.py
pixabay/query.py
pixabay/video.py
pixabay.egg-info/PKG-INFO
pixabay.egg-info/SOURCES.txt
pixabay.egg-info/dependency_links.txt
pixabay.egg-info/requires.txt
pixabay.egg-info/top_level.txt