Metadata-Version: 2.1
Name: pixabay
Version: 0.0.4
Summary: Unofficial python pixabay API client
Home-page: https://github.com/Lukas0025/python-pixabay
Author: Lukáš Plevač
Author-email: lukas@plevac.eu
Classifier: Programming Language :: Python :: 3
Classifier: License :: OSI Approved :: Apache Software License
Classifier: Operating System :: OS Independent
Requires-Python: >=3.0
License-File: LICENSE
